02_sequential_basics/02_02_single_and_double_rate_fibonacci/02_02_single_and_double_rate_fibonacci.sv
//----------------------------------------------------------------------------
// Example
//----------------------------------------------------------------------------

module fibonacci
(
  input               clk,
  input               rst,
  output reg [15:0] num,
  output reg [15:0] num2
);

  always_ff @ (posedge clk)
    if (rst)
      { num, num2 } <= { 16'd1, 16'd1 };
    else
      { num, num2 } <= { num2, num + num2 };

endmodule

//----------------------------------------------------------------------------
// Task
//----------------------------------------------------------------------------

module fibonacci_2
(
  input               clk,
  input               rst,
  output reg [15:0] num,
  output reg [15:0] num2
);
  reg [15:0] num_holder;

  // Task:
  // Implement a module that generates two fibonacci numbers per cycle

  always @(posedge clk ) begin
    if (rst) begin
      num <= 16'd1;
      num2 <= 16'd1;
    end
    else begin
      num_holder = num;
      num <= num2;
      num2 <= num2 + num_holder;
    end
  end

endmodule

02_sequential_basics/02_02_single_and_double_rate_fibonacci/testbench.v
`include "02_02_single_and_double_rate_fibonacci.sv"

module testbench;

  logic clk, rst;
  wire [15:0] f1_num, f1_num2, f2_num, f2_num2;

  fibonacci f1 (.clk(clk), .rst(rst), .num(f1_num), .num2(f1_num2));
  fibonacci_2 f2 (.clk(clk), .rst(rst), .num(f2_num), .num2(f2_num2));

  initial begin
    clk = 0;
    forever #5 clk = ~clk;
  end

  initial begin
    rst = 1;
    #10;
    rst = 0;
  end

  

  initial begin
    $dumpfile("design.vcd");
    $dumpvars(1, testbench);
    #1000;
    $finish;
  end

endmodule

02_sequential_basics/02_02_single_and_double_rate_fibonacci/design.vcd
$date
	Tue Mar 18 11:20:41 2025
$end
$version
	Icarus Verilog
$end
$timescale
	1s
$end
$scope module testbench $end
$var wire 16 ! f2_num2 [15:0] $end
$var wire 16 " f2_num [15:0] $end
$var wire 16 # f1_num2 [15:0] $end
$var wire 16 $ f1_num [15:0] $end
$var reg 1 % clk $end
$var reg 1 & rst $end
$upscope $end
$enddefinitions $end
$comment Show the parameter values. $end
$dumpall
$end
#0
$dumpvars
1&
0%
bx $
bx #
bx "
bx !
$end
#5
b1 $
b1 #
b1 !
b1 "
1%
#10
0%
0&
#15
b10 !
b10 #
1%
#20
0%
#25
b10 $
b11 #
b11 !
b10 "
1%
#30
0%
#35
b101 !
b11 "
b11 $
b101 #
1%
#40
0%
#45
b101 $
b1000 #
b1000 !
b101 "
1%
#50
0%
#55
b1101 !
b1000 "
b1000 $
b1101 #
1%
#60
0%
#65
b1101 $
b10101 #
b10101 !
b1101 "
1%
#70
0%
#75
b100010 !
b10101 "
b10101 $
b100010 #
1%
#80
0%
#85
b100010 $
b110111 #
b110111 !
b100010 "
1%
#90
0%
#95
b1011001 !
b110111 "
b110111 $
b1011001 #
1%
#100
0%
#105
b1011001 $
b10010000 #
b10010000 !
b1011001 "
1%
#110
0%
#115
b11101001 !
b10010000 "
b10010000 $
b11101001 #
1%
#120
0%
#125
b11101001 $
b101111001 #
b101111001 !
b11101001 "
1%
#130
0%
#135
b1001100010 !
b101111001 "
b101111001 $
b1001100010 #
1%
#140
0%
#145
b1001100010 $
b1111011011 #
b1111011011 !
b1001100010 "
1%
#150
0%
#155
b11000111101 !
b1111011011 "
b1111011011 $
b11000111101 #
1%
#160
0%
#165
b11000111101 $
b101000011000 #
b101000011000 !
b11000111101 "
1%
#170
0%
#175
b1000001010101 !
b101000011000 "
b101000011000 $
b1000001010101 #
1%
#180
0%
#185
b1000001010101 $
b1101001101101 #
b1101001101101 !
b1000001010101 "
1%
#190
0%
#195
b10101011000010 !
b1101001101101 "
b1101001101101 $
b10101011000010 #
1%
#200
0%
#205
b10101011000010 $
b100010100101111 #
b100010100101111 !
b10101011000010 "
1%
#210
0%
#215
b110111111110001 !
b100010100101111 "
b100010100101111 $
b110111111110001 #
1%
#220
0%
#225
b110111111110001 $
b1011010100100000 #
b1011010100100000 !
b110111111110001 "
1%
#230
0%
#235
b10010100010001 !
b1011010100100000 "
b1011010100100000 $
b10010100010001 #
1%
#240
0%
#245
b10010100010001 $
b1101101000110001 #
b1101101000110001 !
b10010100010001 "
1%
#250
0%
#255
b1111111101000010 !
b1101101000110001 "
b1101101000110001 $
b1111111101000010 #
1%
#260
0%
#265
b1111111101000010 $
b1101100101110011 #
b1101100101110011 !
b1111111101000010 "
1%
#270
0%
#275
b1101100010110101 !
b1101100101110011 "
b1101100101110011 $
b1101100010110101 #
1%
#280
0%
#285
b1101100010110101 $
b1011001000101000 #
b1011001000101000 !
b1101100010110101 "
1%
#290
0%
#295
b1000101011011101 !
b1011001000101000 "
b1011001000101000 $
b1000101011011101 #
1%
#300
0%
#305
b1000101011011101 $
b11110100000101 #
b11110100000101 !
b1000101011011101 "
1%
#310
0%
#315
b1100011111100010 !
b11110100000101 "
b11110100000101 $
b1100011111100010 #
1%
#320
0%
#325
b1100011111100010 $
b10011100111 #
b10011100111 !
b1100011111100010 "
1%
#330
0%
#335
b1100110011001001 !
b10011100111 "
b10011100111 $
b1100110011001001 #
1%
#340
0%
#345
b1100110011001001 $
b1101000110110000 #
b1101000110110000 !
b1100110011001001 "
1%
#350
0%
#355
b1001111001111001 !
b1101000110110000 "
b1101000110110000 $
b1001111001111001 #
1%
#360
0%
#365
b1001111001111001 $
b111000000101001 #
b111000000101001 !
b1001111001111001 "
1%
#370
0%
#375
b111010100010 !
b111000000101001 "
b111000000101001 $
b111010100010 #
1%
#380
0%
#385
b111010100010 $
b111111011001011 #
b111111011001011 !
b111010100010 "
1%
#390
0%
#395
b1000110101101101 !
b111111011001011 "
b111111011001011 $
b1000110101101101 #
1%
#400
0%
#405
b1000110101101101 $
b110000111000 #
b110000111000 !
b1000110101101101 "
1%
#410
0%
#415
b1001100110100101 !
b110000111000 "
b110000111000 $
b1001100110100101 #
1%
#420
0%
#425
b1001100110100101 $
b1010010111011101 #
b1010010111011101 !
b1001100110100101 "
1%
#430
0%
#435
b11111110000010 !
b1010010111011101 "
b1010010111011101 $
b11111110000010 #
1%
#440
0%
#445
b11111110000010 $
b1110010101011111 #
b1110010101011111 !
b11111110000010 "
1%
#450
0%
#455
b10010011100001 !
b1110010101011111 "
b1110010101011111 $
b10010011100001 #
1%
#460
0%
#465
b10010011100001 $
b101001000000 #
b101001000000 !
b10010011100001 "
1%
#470
0%
#475
b10111100100001 !
b101001000000 "
b101001000000 $
b10111100100001 #
1%
#480
0%
#485
b10111100100001 $
b11100101100001 #
b11100101100001 !
b10111100100001 "
1%
#490
0%
#495
b110100010000010 !
b11100101100001 "
b11100101100001 $
b110100010000010 #
1%
#500
0%
#505
b110100010000010 $
b1010000111100011 #
b1010000111100011 !
b110100010000010 "
1%
#510
0%
#515
b101001100101 !
b1010000111100011 "
b1010000111100011 $
b101001100101 #
1%
#520
0%
#525
b101001100101 $
b1010110001001000 #
b1010110001001000 !
b101001100101 "
1%
#530
0%
#535
b1011011010101101 !
b1010110001001000 "
b1010110001001000 $
b1011011010101101 #
1%
#540
0%
#545
b1011011010101101 $
b110001011110101 #
b110001011110101 !
b1011011010101101 "
1%
#550
0%
#555
b1100110100010 !
b110001011110101 "
b110001011110101 $
b1100110100010 #
1%
#560
0%
#565
b1100110100010 $
b111110010010111 #
b111110010010111 !
b1100110100010 "
1%
#570
0%
#575
b1001011000111001 !
b111110010010111 "
b111110010010111 $
b1001011000111001 #
1%
#580
0%
#585
b1001011000111001 $
b1001011010000 #
b1001011010000 !
b1001011000111001 "
1%
#590
0%
#595
b1010100100001001 !
b1001011010000 "
b1001011010000 $
b1010100100001001 #
1%
#600
0%
#605
b1010100100001001 $
b1011101111011001 #
b1011101111011001 !
b1010100100001001 "
1%
#610
0%
#615
b110010011100010 !
b1011101111011001 "
b1011101111011001 $
b110010011100010 #
1%
#620
0%
#625
b110010011100010 $
b10000010111011 #
b10000010111011 !
b110010011100010 "
1%
#630
0%
#635
b1000010110011101 !
b10000010111011 "
b10000010111011 $
b1000010110011101 #
1%
#640
0%
#645
b1000010110011101 $
b1010011001011000 #
b1010011001011000 !
b1000010110011101 "
1%
#650
0%
#655
b10101111110101 !
b1010011001011000 "
b1010011001011000 $
b10101111110101 #
1%
#660
0%
#665
b10101111110101 $
b1101001001001101 #
b1101001001001101 !
b10101111110101 "
1%
#670
0%
#675
b1111111001000010 !
b1101001001001101 "
b1101001001001101 $
b1111111001000010 #
1%
#680
0%
#685
b1111111001000010 $
b1101000010001111 #
b1101000010001111 !
b1111111001000010 "
1%
#690
0%
#695
b1100111011010001 !
b1101000010001111 "
b1101000010001111 $
b1100111011010001 #
1%
#700
0%
#705
b1100111011010001 $
b1001111101100000 #
b1001111101100000 !
b1100111011010001 "
1%
#710
0%
#715
b110111000110001 !
b1001111101100000 "
b1001111101100000 $
b110111000110001 #
1%
#720
0%
#725
b110111000110001 $
b110110010001 #
b110110010001 !
b110111000110001 "
1%
#730
0%
#735
b111101111000010 !
b110110010001 "
b110110010001 $
b111101111000010 #
1%
#740
0%
#745
b111101111000010 $
b1000100101010011 #
b1000100101010011 !
b111101111000010 "
1%
#750
0%
#755
b10100010101 !
b1000100101010011 "
b1000100101010011 $
b10100010101 #
1%
#760
0%
#765
b10100010101 $
b1000111001101000 #
b1000111001101000 !
b10100010101 "
1%
#770
0%
#775
b1001001101111101 !
b1000111001101000 "
b1000111001101000 $
b1001001101111101 #
1%
#780
0%
#785
b1001001101111101 $
b10000111100101 #
b10000111100101 !
b1001001101111101 "
1%
#790
0%
#795
b1011010101100010 !
b10000111100101 "
b10000111100101 $
b1011010101100010 #
1%
#800
0%
#805
b1011010101100010 $
b1101011101000111 #
b1101011101000111 !
b1011010101100010 "
1%
#810
0%
#815
b1000110010101001 !
b1101011101000111 "
b1101011101000111 $
b1000110010101001 #
1%
#820
0%
#825
b1000110010101001 $
b110001111110000 #
b110001111110000 !
b1000110010101001 "
1%
#830
0%
#835
b1111000010011001 !
b110001111110000 "
b110001111110000 $
b1111000010011001 #
1%
#840
0%
#845
b1111000010011001 $
b101010010001001 #
b101010010001001 !
b1111000010011001 "
1%
#850
0%
#855
b100010100100010 !
b101010010001001 "
b101010010001001 $
b100010100100010 #
1%
#860
0%
#865
b100010100100010 $
b1001100110101011 #
b1001100110101011 !
b100010100100010 "
1%
#870
0%
#875
b1101111011001101 !
b1001100110101011 "
b1001100110101011 $
b1101111011001101 #
1%
#880
0%
#885
b1101111011001101 $
b111100001111000 #
b111100001111000 !
b1101111011001101 "
1%
#890
0%
#895
b101011101000101 !
b111100001111000 "
b111100001111000 $
b101011101000101 #
1%
#900
0%
#905
b101011101000101 $
b1100111110111101 #
b1100111110111101 !
b101011101000101 "
1%
#910
0%
#915
b10011100000010 !
b1100111110111101 "
b1100111110111101 $
b10011100000010 #
1%
#920
0%
#925
b10011100000010 $
b1111011010111111 #
b1111011010111111 !
b10011100000010 "
1%
#930
0%
#935
b1110111000001 !
b1111011010111111 "
b1111011010111111 $
b1110111000001 #
1%
#940
0%
#945
b1110111000001 $
b1010010000000 #
b1010010000000 !
b1110111000001 "
1%
#950
0%
#955
b11001001000001 !
b1010010000000 "
b1010010000000 $
b11001001000001 #
1%
#960
0%
#965
b11001001000001 $
b100011011000001 #
b100011011000001 !
b11001001000001 "
1%
#970
0%
#975
b111100100000010 !
b100011011000001 "
b100011011000001 $
b111100100000010 #
1%
#980
0%
#985
b111100100000010 $
b1011111111000011 #
b1011111111000011 !
b111100100000010 "
1%
#990
0%
#995
b11100011000101 !
b1011111111000011 "
b1011111111000011 $
b11100011000101 #
1%
